client/__init__.py
client/client.py
client/client_database.py
client/client_gui.py
client/decorators.py
client/descriptors.py
client/main_window_conv.py
client/metaclasses.py
client/start_dialog.py
client/common/__init__.py
client/common/utils.py
client/common/variables.py
client/log/__init__.py
client/log/client_log_config.py
py_danil_client-0.0.1.data/scripts/client_run
py_danil_client-0.0.1.dist-info/METADATA
py_danil_client-0.0.1.dist-info/WHEEL
py_danil_client-0.0.1.dist-info/top_level.txt
py_danil_client-0.0.1.dist-info/RECORD
